sanjuuni/__init__.cp314-win_arm64.pyd
sanjuuni/__init__.pyi
sanjuuni-0.1.1.dist-info/licenses/LICENSE
sanjuuni-0.1.1.dist-info/METADATA
sanjuuni-0.1.1.dist-info/WHEEL
sanjuuni-0.1.1.dist-info/top_level.txt
sanjuuni-0.1.1.dist-info/RECORD
