Metadata-Version: 2.4
Name: sanjuuni
Version: 0.1.1
Summary: Converts images and videos into a format suitable for ComputerCraft, based on sanjuuni.
Author-email: JackMacWindows <jackmacwindowslinux@gmail.com>
License-Expression: GPL-2.0-or-later
Keywords: computercraft,images
Classifier: Programming Language :: Python :: 3
Classifier: Topic :: Multimedia :: Graphics :: Graphics Conversion
Requires-Python: >=3.12
License-File: LICENSE
Dynamic: license-file
